[
    {
        "original": "고",
        "transformed": "ㄸ"
    },
    {
        "original": "끄",
        "transformed": "ㄸ"
    },
    {
        "original": "구",
        "transformed": "亡"
    },
    {
        "original": "구룡마을",
        "transformed": "릉ㅓㅁ율亡"
    },
    {
        "original": "곰",
        "transformed": "문"
    },
    {
        "original": "국",
        "transformed": "논"
    },
    {
        "original": "공용물품",
        "transformed": "뫂롬융운"
    },
    {
        "original": "굥",
        "transformed": "윤"
    },
    {
        "original": "풍운",
        "transformed": "공옾"
    },
    {
        "original": "어",
        "transformed": "ㅏㅇ"
    },
    {
        "original": "육군",
        "transformed": "곤뇽"
    },
    {
        "original": "공군",
        "transformed": "곤운"
    },
    {
        "original": "곰국",
        "transformed": "논문"
    },
    {
        "original": "운율",
        "transformed": "룡공"
    },
    {
        "original": "물론",
        "transformed": "굴롬"
    },
    {
        "original": "구몬",
        "transformed": "굼亡"
    },
    {
        "original": "골룸",
        "transformed": "몰룬"
    },
    {
        "original": "녹음",
        "transformed": "믕눅"
    },
    {
        "original": "금융",
        "transformed": "용믄"
    },
    {
        "original": "능글",
        "transformed": "른윽"
    },
    {
        "original": "육근옥",
        "transformed": "눙근뇽"
    },
    {
        "original": "개새끼",
        "transformed": "ILL HV HL"
    },
    {
        "original": "논공",
        "transformed": "운국"
    },
    {
        "original": "오목",
        "transformed": "눔ꅂ"
    },
    {
        "original": "폭음룡",
        "transformed": "율믕눞"
    },
    {
        "original": "디씨",
        "transformed": "IWㅁ"
    },
    {
        "original": "금물",
        "transformed": "롬믄"
    },
    {
        "original": "폭풍",
        "transformed": "옾눞"
    },
    {
        "original": "눈물",
        "transformed": "롬곡"
    },
    {
        "original": "폭풍눈물",
        "transformed": "롬곡옾눞"
    },
    {
        "original": "굴욕",
        "transformed": "늉론"
    },
    {
        "original": "폭풍굴욕",
        "transformed": "늉론옾눞"
    },
    {
        "original": "폭풍저그",
        "transformed": "匸ㅏㅛ옾눞"
    },
    {
        "original": "시공의 폭풍",
        "transformed": "옾눞 Iㆆ운IV"
    },
    {
        "original": "오늘은 영국이다",
        "transformed": "ㅓ⊃IO논ꄗㅇ 긍륵ꅂ"
    },
    {
        "original": "모히또에서 몰디브 한 잔",
        "transformed": "ㅓ교 ㅋ우 Āㅁ룸 ㅏVIЮ五I우石"
    },
    {
        "original": "능금",
        "transformed": "믄윽"
    },
    {
        "original": "너 그리고 나",
        "transformed": "ㅓㄱ 띠ㄹ匸 ㅏㄱ"
    },
    {
        "original": "물",
        "transformed": "롬"
    },
    {
        "original": "근육",
        "transformed": "뇽근"
    },
    {
        "original": "눈높이",
        "transformed": "IO푹곡"
    },
    {
        "original": "눈높이",
        "transformed": "ㅣㅇ푹곡"
    },
    {
        "original": "능률",
        "transformed": "룔윽"
    },
    {
        "original": "용궁",
        "transformed": "온융"
    },
    {
        "original": "온몸",
        "transformed": "뭄궁"
    },
    {
        "original": "몽골",
        "transformed": "룬움"
    },
    {
        "original": "공룡",
        "transformed": "율운"
    },
    {
        "original": "몰폰",
        "transformed": "궆룸"
    },
    {
        "original": "골목",
        "transformed": "눔룬"
    },
    {
        "original": "어머니",
        "transformed": "ㅣㄱㅏㅁㅏㅇ"
    },
    {
        "original": "아버지",
        "transformed": "ㅣㅛㅏAㅓO"
    },
    {
        "original": "어버이",
        "transformed": "IOㅏAㅏO"
    },
    {
        "original": "폰",
        "transformed": "궆"
    },
    {
        "original": "울릉군",
        "transformed": "곤을롱"
    },
    {
        "original": "목욕",
        "transformed": "늉눔"
    },
    {
        "original": "목욕용품",
        "transformed": "뫂융늉눔"
    },
    {
        "original": "물품",
        "transformed": "뫂롬"
    },
    {
        "original": "이새롬",
        "transformed": "물HVIO"
    },
    {
        "original": "음운론",
        "transformed": "굴공믕"
    },
    {
        "original": "목공풀",
        "transformed": "롶운눔"
    },
    {
        "original": "아이폰",
        "transformed": "궆IOㅓO"
    },
    {
        "original": "이어폰",
        "transformed": "궆ㅏㅇIO"
    },
    {
        "original": "옹기",
        "transformed": "IL웅"
    },
    {
        "original": "농구공",
        "transformed": "운亡욱"
    },
    {
        "original": "아시아",
        "transformed": "ㅓOIVㅓO"
    },
    {
        "original": "미국",
        "transformed": "논ㅣㅁ"
    },
    {
        "original": "카리나",
        "transformed": "ㅓㄱㅣㄹㅓ匕"
    },
    {
        "original": "카데나",
        "transformed": "ㅓㄱㅣㅏコㅓ匕"
    },
    {
        "original": "문은율",
        "transformed": "룡긍곰"
    },
    {
        "original": "문재인",
        "transformed": "I∂Hと곰"
    },
    {
        "original": "또치",
        "transformed": "IҰ五"
    },
    {
        "original": "카이저",
        "transformed": "ㅏㅛㅣㅇㅓ匕"
    },
    {
        "original": "리어카",
        "transformed": "ㅓ匕ㅏㅇIㄹ"
    },
    {
        "original": "목지",
        "transformed": "ㅣと눔"
    },
    {
        "original": "공굴리기",
        "transformed": "ㅣㄴㅣㄹ론운"
    },
    {
        "original": "군내",
        "transformed": "ㅐㄱ곤"
    },
    {
        "original": "물대",
        "transformed": "ㅐ그롬"
    },
    {
        "original": "굴지",
        "transformed": "ㅣと론"
    },
    {
        "original": "몽리자",
        "transformed": "ㅓとㅣㄹ움"
    },
    {
        "original": "풍어기",
        "transformed": "ㅣㄴㅏㅇ옾"
    },
    {
        "original": "목재",
        "transformed": "ㅐと눔"
    },
    {
        "original": "애국자",
        "transformed": "ㅓと논ㅐㅇ"
    },
    {
        "original": "용저",
        "transformed": "ㅏと융"
    },
    {
        "original": "물바래",
        "transformed": "ㅐㄹㅓA롬"
    },
    {
        "original": "제군자",
        "transformed": "ㅓと곤ㅣㅏと"
    },
    {
        "original": "내국",
        "transformed": "논ㅐㄱ"
    },
    {
        "original": "굴저냐",
        "transformed": "ㅕㄱㅏと론"
    },
    {
        "original": "거풍",
        "transformed": "옾ㅏㄴ"
    },
    {
        "original": "국지풍",
        "transformed": "옾ㅣと논"
    },
    {
        "original": "미레그물",
        "transformed": "롬匸ㅣㅏㄹㅣㅁ"
    },
    {
        "original": "계품",
        "transformed": "뫂ㅣㅑㄴ"
    },
    {
        "original": "공공녹지",
        "transformed": "ㅣと눅운운"
    },
    {
        "original": "마공",
        "transformed": "운ㅓㅁ"
    },
    {
        "original": "애용",
        "transformed": "융ㅐㅇ"
    },
    {
        "original": "에움",
        "transformed": "몽ㅣㅏㅇ"
    },
    {
        "original": "웅사",
        "transformed": "ㅓV옹"
    },
    {
        "original": "곡예사",
        "transformed": "ㅓVㅣㅑㅇ눈"
    },
    {
        "original": "문기",
        "transformed": "ㅣㄴ곰"
    },
    {
        "original": "지운",
        "transformed": "공ㅣと"
    },
    {
        "original": "배움배움",
        "transformed": "몽ㅐA몽ㅐA"
    },
    {
        "original": "사대문",
        "transformed": "곰ㅐ그ㅓV"
    },
    {
        "original": "눈가리개",
        "transformed": "ㅐㄴㅣㄹㅓㄴ곡"
    },
    {
        "original": "깨나물",
        "transformed": "롬ㅓㄱㅐㄴㄴ"
    },
    {
        "original": "물어미",
        "transformed": "ㅣㅁㅏㅇ롬"
    },
    {
        "original": "파공",
        "transformed": "운ㅓㅍ"
    },
    {
        "original": "겨울비",
        "transformed": "ㅣA롱ㅑㄴ"
    },
    {
        "original": "내아문",
        "transformed": "곰ㅓㅇㅐㄱ"
    },
    {
        "original": "재욕",
        "transformed": "늉ㅐと"
    },
    {
        "original": "내공미",
        "transformed": "ㅣㅁ운ㅐㄱ"
    },
    {
        "original": "시골",
        "transformed": "룬ㅣV"
    },
    {
        "original": "서울띠기",
        "transformed": "ㅣㄴㅣ그그롱ㅏV"
    },
    {
        "original": "개울",
        "transformed": "롱ㅐㄴ"
    },
    {
        "original": "몰이",
        "transformed": "ㅣㅇ룸"
    },
    {
        "original": "개운",
        "transformed": "공ㅐㄴ"
    },
    {
        "original": "해울",
        "transformed": "롱ㅐ우"
    },
    {
        "original": "눈꺼풀",
        "transformed": "롶ㅏㄴㄴ곡"
    },
    {
        "original": "묵비지",
        "transformed": "ㅣとㅣA놈"
    },
    {
        "original": "묵허",
        "transformed": "ㅏ우놈"
    },
    {
        "original": "애기비녀골",
        "transformed": "룬ㅑㄱㅣAㅣㄴㅐㅇ"
    },
    {
        "original": "운하",
        "transformed": "ㅓ우공"
    },
    {
        "original": "용해",
        "transformed": "ㅐ우융"
    },
    {
        "original": "높게더기",
        "transformed": "ㅣㄴㅏ그ㅣㅏㄴ푹"
    },
    {
        "original": "태공",
        "transformed": "운ㅐ彐"
    },
    {
        "original": "농해",
        "transformed": "ㅐ우욱"
    },
    {
        "original": "목패",
        "transformed": "ㅐㅍ눔"
    },
    {
        "original": "농태",
        "transformed": "ㅐ彐욱"
    },
    {
        "original": "지농",
        "transformed": "욱ㅣと"
    },
    {
        "original": "사골",
        "transformed": "룬ㅓV"
    },
    {
        "original": "굴대",
        "transformed": "ㅐ그론"
    },
    {
        "original": "내풍",
        "transformed": "옾ㅐㄱ"
    },
    {
        "original": "새웅",
        "transformed": "옹ㅐV"
    },
    {
        "original": "눈씨",
        "transformed": "ㅣW곡"
    },
    {
        "original": "대곤",
        "transformed": "군ㅐ그"
    },
    {
        "original": "국물재비",
        "transformed": "ㅣAㅐと롬논"
    },
    {
        "original": "대문",
        "transformed": "곰ㅐ그"
    },
    {
        "original": "개국",
        "transformed": "논ㅐㄴ"
    },
    {
        "original": "때물",
        "transformed": "롬ㅐ그그"
    },
    {
        "original": "개세지풍",
        "transformed": "옾ㅣとㅣㅏVㅐㄴ"
    },
    {
        "original": "몰사",
        "transformed": "ㅓV룸"
    },
    {
        "original": "문려",
        "transformed": "ㅑㄹ곰"
    },
    {
        "original": "용례",
        "transformed": "ㅣㅑㄹ융"
    },
    {
        "original": "궁례",
        "transformed": "ㅣㅑㄹ온"
    },
    {
        "original": "제재품",
        "transformed": "뫂ㅐとㅣㅏと"
    },
    {
        "original": "문라",
        "transformed": "ㅓㄹ곰"
    },
    {
        "original": "아례곡",
        "transformed": "눈ㅣㅑㄹㅓㅇ"
    },
    {
        "original": "군자가",
        "transformed": "ㅓㄴㅓと곤"
    },
    {
        "original": "자국제어",
        "transformed": "ㅏㅇㅣㅏと논ㅓと"
    },
    {
        "original": "올눌제",
        "transformed": "ㅣㅏと록룽"
    },
    {
        "original": "겨울",
        "transformed": "롱ㅑㄴ"
    },
    {
        "original": "제웅",
        "transformed": "옹ㅣㅏと"
    },
    {
        "original": "거폭",
        "transformed": "눞ㅏㄴ"
    },
    {
        "original": "싸움",
        "transformed": "몽ㅓW"
    },
    {
        "original": "묵거",
        "transformed": "ㅏㄴ놈"
    },
    {
        "original": "용미",
        "transformed": "ㅣㅁ융"
    },
    {
        "original": "예용",
        "transformed": "융ㅣㅑㅇ"
    },
    {
        "original": "야욕가",
        "transformed": "ㅓㄴ늉ㅕㅇ"
    },
    {
        "original": "패옥",
        "transformed": "눙ㅐㅍ"
    },
    {
        "original": "개굴",
        "transformed": "론ㅐㄴ"
    },
    {
        "original": "문하녹사",
        "transformed": "ㅓV눅ㅓ우곰"
    },
    {
        "original": "재목",
        "transformed": "눔ㅐと"
    },
    {
        "original": "사이골",
        "transformed": "룬ㅣㅇㅓV"
    },
    {
        "original": "풀씨",
        "transformed": "ㅣW롶"
    },
    {
        "original": "공시태",
        "transformed": "ㅐ彐ㅣV운"
    },
    {
        "original": "물아래",
        "transformed": "ㅐㄹㅓㅇ롬"
    },
    {
        "original": "다용",
        "transformed": "융ㅓ그"
    },
    {
        "original": "군국제",
        "transformed": "ㅣㅏと논곤"
    },
    {
        "original": "사용세",
        "transformed": "ㅣㅏV융ㅓV"
    },
    {
        "original": "공패",
        "transformed": "ㅐㅍ운"
    },
    {
        "original": "몽자",
        "transformed": "ㅓと움"
    },
    {
        "original": "서국",
        "transformed": "논ㅏV"
    },
    {
        "original": "하사품",
        "transformed": "뫂ㅓVㅓ우"
    },
    {
        "original": "목배",
        "transformed": "ㅐA눔"
    },
    {
        "original": "제눈",
        "transformed": "곡ㅣㅏと"
    },
    {
        "original": "지피물",
        "transformed": "롬ㅣㅍㅣと"
    },
    {
        "original": "내국제",
        "transformed": "ㅣㅏと논ㅐㄱ"
    },
    {
        "original": "녹거",
        "transformed": "ㅏㄴ눅"
    },
    {
        "original": "사폭",
        "transformed": "눞ㅓV"
    },
    {
        "original": "대저울",
        "transformed": "롱ㅏとㅐ그"
    },
    {
        "original": "군마",
        "transformed": "ㅓㅁ곤"
    },
    {
        "original": "거용",
        "transformed": "융ㅏㄴ"
    },
    {
        "original": "공용어",
        "transformed": "ㅏㅇ융운"
    },
    {
        "original": "농가",
        "transformed": "ㅓㄴ욱"
    },
    {
        "original": "풀게",
        "transformed": "ㅣㅏㄴ롶"
    },
    {
        "original": "기제품",
        "transformed": "뫂ㅣㅏとㅣㄴ"
    },
    {
        "original": "옥개",
        "transformed": "ㅐㄴ눙"
    },
    {
        "original": "물레",
        "transformed": "ㅣㅏㄹ롬"
    },
    {
        "original": "개싸움",
        "transformed": "몽ㅓWㅐㄴ"
    },
    {
        "original": "태몽",
        "transformed": "움ㅐ彐"
    },
    {
        "original": "게눈",
        "transformed": "곡ㅣㅏㄴ"
    },
    {
        "original": "공예가",
        "transformed": "ㅓㄴㅣㅑㅇ운"
    },
    {
        "original": "논개",
        "transformed": "ㅐㄴ국"
    },
    {
        "original": "배문",
        "transformed": "곰ㅐA"
    },
    {
        "original": "이용품",
        "transformed": "뫂융ㅣㅇ"
    },
    {
        "original": "운라",
        "transformed": "ㅓㄹ공"
    },
    {
        "original": "사온",
        "transformed": "궁ㅓV"
    },
    {
        "original": "목어",
        "transformed": "ㅏㅇ눔"
    },
    {
        "original": "개국공",
        "transformed": "운논ㅐㄴ"
    },
    {
        "original": "시운목",
        "transformed": "눔공ㅣV"
    },
    {
        "original": "혜풍",
        "transformed": "옾ㅣㅑ우"
    },
    {
        "original": "목저",
        "transformed": "ㅏと눔"
    },
    {
        "original": "여울",
        "transformed": "롱ㅑㅇ"
    },
    {
        "original": "물버러지",
        "transformed": "ㅣとㅏㄹㅏA롬"
    },
    {
        "original": "기온",
        "transformed": "궁ㅣㄴ"
    },
    {
        "original": "자라풀",
        "transformed": "롶ㅓㄹㅓと"
    },
    {
        "original": "새그물",
        "transformed": "롬匸ㅐV"
    },
    {
        "original": "용재",
        "transformed": "ㅐと융"
    },
    {
        "original": "이풀",
        "transformed": "롶ㅣㅇ"
    },
    {
        "original": "해궁",
        "transformed": "온ㅐ우"
    },
    {
        "original": "미문",
        "transformed": "곰ㅣㅁ"
    },
    {
        "original": "옥폐",
        "transformed": "ㅣㅑㅍ눙"
    },
    {
        "original": "녹시사",
        "transformed": "ㅓVㅣV눅"
    },
    {
        "original": "세곡미",
        "transformed": "ㅣㅁ눈ㅣㅏV"
    },
    {
        "original": "세웅",
        "transformed": "옹ㅣㅏV"
    },
    {
        "original": "폐군",
        "transformed": "곤ㅣㅑㅍ"
    },
    {
        "original": "그리움",
        "transformed": "몽ㅣㄹ匸"
    },
    {
        "original": "풀매",
        "transformed": "ㅐㅁ롶"
    },
    {
        "original": "허물",
        "transformed": "롬ㅏ우"
    },
    {
        "original": "목베개",
        "transformed": "ㅐㄴㅣㅏA눔"
    },
    {
        "original": "묵해",
        "transformed": "ㅐ우놈"
    },
    {
        "original": "자곡",
        "transformed": "눈ㅓと"
    },
    {
        "original": "해몽자",
        "transformed": "ㅓと움ㅐ우"
    },
    {
        "original": "옥새",
        "transformed": "ㅐV눙"
    },
    {
        "original": "옹가",
        "transformed": "ㅓㄴ웅"
    },
    {
        "original": "서대문",
        "transformed": "곰ㅐ그ㅏV"
    },
    {
        "original": "타곡",
        "transformed": "눈ㅓ彐"
    },
    {
        "original": "폐기물",
        "transformed": "롬ㅣㄴㅣㅑㅍ"
    },
    {
        "original": "몸매",
        "transformed": "ㅐㅁ뭄"
    },
    {
        "original": "미국",
        "transformed": "논ㅣㅁ"
    },
    {
        "original": "운세",
        "transformed": "ㅣㅏV공"
    },
    {
        "original": "개품",
        "transformed": "뫂ㅐㄴ"
    },
    {
        "original": "허목",
        "transformed": "눔ㅏ우"
    },
    {
        "original": "파문",
        "transformed": "곰ㅓㅍ"
    },
    {
        "original": "용세",
        "transformed": "ㅣㅏV융"
    },
    {
        "original": "가재기물",
        "transformed": "롬ㅣㄴㅐとㅓㄴ"
    },
    {
        "original": "곡례",
        "transformed": "ㅣㅑㄹ눈"
    },
    {
        "original": "타문",
        "transformed": "곰ㅓ彐"
    },
    {
        "original": "문리대",
        "transformed": "ㅐ그ㅣㄹ곰"
    },
    {
        "original": "나올",
        "transformed": "룽ㅓㄱ"
    },
    {
        "original": "비골",
        "transformed": "룬ㅣA"
    },
    {
        "original": "여공지사",
        "transformed": "ㅓVㅣと운ㅑㅇ"
    },
    {
        "original": "내폭제",
        "transformed": "ㅣㅏと눞ㅐㄱ"
    },
    {
        "original": "용가",
        "transformed": "ㅓㄴ융"
    },
    {
        "original": "대용품",
        "transformed": "뫂융ㅐ그"
    },
    {
        "original": "물품사",
        "transformed": "ㅓV뫂롬"
    },
    {
        "original": "묵대",
        "transformed": "ㅐ그놈"
    },
    {
        "original": "옥기",
        "transformed": "ㅣㄴ눙"
    },
    {
        "original": "지물",
        "transformed": "롬ㅣと"
    },
    {
        "original": "옥허궁",
        "transformed": "온ㅏ우눙"
    },
    {
        "original": "군기시",
        "transformed": "ㅣVㅣㄴ곤"
    },
    {
        "original": "제욕",
        "transformed": "늉ㅣㅏと"
    },
    {
        "original": "계곡",
        "transformed": "눈ㅣㅑㄴ"
    },
    {
        "original": "예비품",
        "transformed": "뫂ㅣAㅣㅑㅇ"
    },
    {
        "original": "지시물",
        "transformed": "롬ㅣVㅣと"
    },
    {
        "original": "공미",
        "transformed": "ㅣㅁ운"
    },
    {
        "original": "시제품",
        "transformed": "뫂ㅣㅏとㅣV"
    },
    {
        "original": "곡미",
        "transformed": "ㅣㅁ눈"
    },
    {
        "original": "제용사",
        "transformed": "ㅓV융ㅣㅏと"
    },
    {
        "original": "물미거지",
        "transformed": "ㅣとㅏㄴㅣㅁ롬"
    },
    {
        "original": "운예",
        "transformed": "ㅣㅑㅇ공"
    },
    {
        "original": "씨올",
        "transformed": "룽ㅣW"
    },
    {
        "original": "어깨싸움",
        "transformed": "몽ㅓWㅐㄴㄴㅏㅇ"
    },
    {
        "original": "운재공",
        "transformed": "운ㅐと공"
    },
    {
        "original": "몰세",
        "transformed": "ㅣㅏV룸"
    },
    {
        "original": "공례",
        "transformed": "ㅣㅑㄹ운"
    },
    {
        "original": "옥공예",
        "transformed": "ㅣㅑㅇ운눙"
    },
    {
        "original": "대옹",
        "transformed": "웅ㅐ그"
    },
    {
        "original": "허공계",
        "transformed": "ㅣㅑㄴ운ㅏ우"
    },
    {
        "original": "여재문",
        "transformed": "곰ㅐとㅑㅇ"
    },
    {
        "original": "용문사",
        "transformed": "ㅓV곰융"
    },
    {
        "original": "옥계",
        "transformed": "ㅣㅑㄴ눙"
    },
    {
        "original": "묵나물",
        "transformed": "롬ㅓㄱ놈"
    },
    {
        "original": "용리제",
        "transformed": "ㅣㅏとㅣㄹ융"
    },
    {
        "original": "새옹",
        "transformed": "웅ㅐV"
    },
    {
        "original": "새골",
        "transformed": "룬ㅐV"
    },
    {
        "original": "허국",
        "transformed": "논ㅏ우"
    },
    {
        "original": "어곤",
        "transformed": "군ㅏㅇ"
    },
    {
        "original": "미목",
        "transformed": "눔ㅣㅁ"
    },
    {
        "original": "농예",
        "transformed": "ㅣㅑㅇ욱"
    },
    {
        "original": "국례",
        "transformed": "ㅣㅑㄹ논"
    },
    {
        "original": "새움",
        "transformed": "몽ㅐV"
    },
    {
        "original": "눈까풀",
        "transformed": "롶ㅓㄴㄴ곡"
    },
    {
        "original": "기운문",
        "transformed": "곰공ㅣㄴ"
    },
    {
        "original": "온대",
        "transformed": "ㅐ그궁"
    },
    {
        "original": "풀내",
        "transformed": "ㅐㄱ롶"
    },
    {
        "original": "바자울",
        "transformed": "롱ㅓとㅓA"
    },
    {
        "original": "파곡",
        "transformed": "눈ㅓㅍ"
    },
    {
        "original": "굴개피",
        "transformed": "ㅣㅍㅐㄴ론"
    },
    {
        "original": "녹이",
        "transformed": "ㅣㅇ눅"
    },
    {
        "original": "개폼",
        "transformed": "뭎ㅐㄴ"
    },
    {
        "original": "물테",
        "transformed": "ㅣㅏ彐롬"
    },
    {
        "original": "몽세",
        "transformed": "ㅣㅏV움"
    },
    {
        "original": "묵재",
        "transformed": "ㅐと놈"
    },
    {
        "original": "폐옥",
        "transformed": "눙ㅣㅑㅍ"
    },
    {
        "original": "매옥",
        "transformed": "눙ㅐㅁ"
    },
    {
        "original": "국태공",
        "transformed": "운ㅐ彐논"
    },
    {
        "original": "군비",
        "transformed": "ㅣA곤"
    },
    {
        "original": "배사곡",
        "transformed": "눈ㅓVㅐA"
    },
    {
        "original": "계궁",
        "transformed": "온ㅣㅑㄴ"
    },
    {
        "original": "해목",
        "transformed": "눔ㅐ우"
    },
    {
        "original": "곡하",
        "transformed": "ㅓ우눈"
    },
    {
        "original": "풍려",
        "transformed": "ㅑㄹ옾"
    },
    {
        "original": "기군",
        "transformed": "곤ㅣㄴ"
    },
    {
        "original": "내물",
        "transformed": "롬ㅐㄱ"
    },
    {
        "original": "기골",
        "transformed": "룬ㅣㄴ"
    },
    {
        "original": "세물",
        "transformed": "롬ㅣㅏV"
    },
    {
        "original": "군폐",
        "transformed": "ㅣㅑㅍ곤"
    },
    {
        "original": "해풍",
        "transformed": "옾ㅐ우"
    },
    {
        "original": "타용",
        "transformed": "융ㅓ彐"
    },
    {
        "original": "사제품",
        "transformed": "뫂ㅣㅏとㅓV"
    },
    {
        "original": "내문",
        "transformed": "곰ㅐㄱ"
    },
    {
        "original": "욕계",
        "transformed": "ㅣㅑㄴ늉"
    },
    {
        "original": "곤마",
        "transformed": "ㅓㅁ군"
    },
    {
        "original": "농거",
        "transformed": "ㅏㄴ욱"
    },
    {
        "original": "물계자가",
        "transformed": "ㅓㄴㅓとㅣㅑㄴ롬"
    },
    {
        "original": "여옹",
        "transformed": "웅ㅑㅇ"
    },
    {
        "original": "자폭",
        "transformed": "눞ㅓと"
    },
    {
        "original": "국비",
        "transformed": "ㅣA논"
    },
    {
        "original": "곡사궁",
        "transformed": "온ㅓV눈"
    },
    {
        "original": "세굴",
        "transformed": "론ㅣㅏV"
    },
    {
        "original": "사리나물",
        "transformed": "롬ㅓㄱㅣㄹㅓV"
    },
    {
        "original": "웅계",
        "transformed": "ㅣㅑㄴ옹"
    },
    {
        "original": "폐목",
        "transformed": "눔ㅣㅑㅍ"
    },
    {
        "original": "타제품",
        "transformed": "뫂ㅣㅏとㅓ彐"
    },
    {
        "original": "공려",
        "transformed": "ㅑㄹ운"
    },
    {
        "original": "해운대",
        "transformed": "ㅐ그공ㅐ우"
    },
    {
        "original": "애용품",
        "transformed": "뫂융ㅐㅇ"
    },
    {
        "original": "하용",
        "transformed": "융ㅓ우"
    },
    {
        "original": "혜공",
        "transformed": "운ㅣㅑ우"
    },
    {
        "original": "저공해",
        "transformed": "ㅐ우운ㅏと"
    },
    {
        "original": "세공품",
        "transformed": "뫂운ㅣㅏV"
    },
    {
        "original": "자가품",
        "transformed": "뫂ㅓㄴㅓと"
    },
    {
        "original": "개국자",
        "transformed": "ㅓと논ㅐㄴ"
    },
    {
        "original": "공허지지",
        "transformed": "ㅣとㅣとㅏ우운"
    },
    {
        "original": "하물",
        "transformed": "롬ㅓ우"
    },
    {
        "original": "서몽",
        "transformed": "움ㅏV"
    },
    {
        "original": "풍물패",
        "transformed": "ㅐㅍ롬옾"
    },
    {
        "original": "기물",
        "transformed": "롬ㅣㄴ"
    },
    {
        "original": "자지곡옥",
        "transformed": "눙눈ㅣとㅓと"
    },
    {
        "original": "공사지계",
        "transformed": "ㅣㅑㄴㅣとㅓV운"
    },
    {
        "original": "목계가",
        "transformed": "ㅓㄴㅣㅑㄴ눔"
    },
    {
        "original": "내용재",
        "transformed": "ㅐと융ㅐㄱ"
    },
    {
        "original": "몸피",
        "transformed": "ㅣㅍ뭄"
    },
    {
        "original": "궁마지재",
        "transformed": "ㅐとㅣとㅓㅁ온"
    },
    {
        "original": "운문사",
        "transformed": "ㅓV곰공"
    },
    {
        "original": "개용",
        "transformed": "융ㅐㄴ"
    },
    {
        "original": "곰페",
        "transformed": "ㅣㅏㅍ문"
    },
    {
        "original": "기욕",
        "transformed": "늉ㅣㄴ"
    },
    {
        "original": "웅거",
        "transformed": "ㅏㄴ옹"
    },
    {
        "original": "농자",
        "transformed": "ㅓと욱"
    },
    {
        "original": "물제기",
        "transformed": "ㅣㄴㅣㅏと롬"
    },
    {
        "original": "목매기",
        "transformed": "ㅣㄴㅐㅁ눔"
    },
    {
        "original": "풍지",
        "transformed": "ㅣと옾"
    },
    {
        "original": "옥제",
        "transformed": "ㅣㅏと눙"
    },
    {
        "original": "새공",
        "transformed": "운ㅐV"
    },
    {
        "original": "재웅",
        "transformed": "옹ㅐと"
    },
    {
        "original": "눌러떼기",
        "transformed": "ㅣㄴㅣㅏ그그ㅏㄹ록"
    },
    {
        "original": "예욕",
        "transformed": "늉ㅣㅑㅇ"
    },
    {
        "original": "미곡계",
        "transformed": "ㅣㅑㄴ눈ㅣㅁ"
    },
    {
        "original": "이공",
        "transformed": "운ㅣㅇ"
    },
    {
        "original": "자계옹",
        "transformed": "웅ㅣㅑㄴㅓと"
    },
    {
        "original": "자욱",
        "transformed": "농ㅓと"
    },
    {
        "original": "재군비",
        "transformed": "ㅣA곤ㅐと"
    },
    {
        "original": "대욕",
        "transformed": "늉ㅐ그"
    },
    {
        "original": "애군",
        "transformed": "곤ㅐㅇ"
    },
    {
        "original": "군례",
        "transformed": "ㅣㅑㄹ곤"
    },
    {
        "original": "애내곡",
        "transformed": "눈ㅐㄱㅐㅇ"
    },
    {
        "original": "눈미나리아재비",
        "transformed": "ㅣAㅐとㅓㅇㅣㄹㅓㄱㅣㅁ곡"
    },
    {
        "original": "물때",
        "transformed": "ㅐ그그롬"
    },
    {
        "original": "비지국",
        "transformed": "논ㅣとㅣA"
    },
    {
        "original": "풍기대",
        "transformed": "ㅐ그ㅣㄴ옾"
    },
    {
        "original": "목공사",
        "transformed": "ㅓV운눔"
    },
    {
        "original": "비목어",
        "transformed": "ㅏㅇ눔ㅣA"
    },
    {
        "original": "개자리골",
        "transformed": "룬ㅣㄹㅓとㅐㄴ"
    },
    {
        "original": "높이재개",
        "transformed": "ㅐㄴㅐとㅣㅇ푹"
    },
    {
        "original": "사용물",
        "transformed": "롬융ㅓV"
    },
    {
        "original": "곡마사",
        "transformed": "ㅓVㅓㅁ눈"
    },
    {
        "original": "패공",
        "transformed": "운ㅐㅍ"
    },
    {
        "original": "옥배",
        "transformed": "ㅐA눙"
    },
    {
        "original": "몸씨",
        "transformed": "ㅣW뭄"
    },
    {
        "original": "목리문",
        "transformed": "곰ㅣㄹ눔"
    },
    {
        "original": "몽예",
        "transformed": "ㅣㅑㅇ움"
    },
    {
        "original": "기곡제",
        "transformed": "ㅣㅏと눈ㅣㄴ"
    },
    {
        "original": "재제품",
        "transformed": "뫂ㅣㅏとㅐと"
    },
    {
        "original": "새미놀이",
        "transformed": "ㅣㅇ룩ㅣㅁㅐV"
    },
    {
        "original": "제폭제",
        "transformed": "ㅣㅏと눞ㅣㅏと"
    },
    {
        "original": "궁태",
        "transformed": "ㅐ彐온"
    },
    {
        "original": "풍해",
        "transformed": "ㅐ우옾"
    },
    {
        "original": "파시풍",
        "transformed": "옾ㅣVㅓㅍ"
    },
    {
        "original": "곤대",
        "transformed": "ㅐ그군"
    },
    {
        "original": "타공",
        "transformed": "운ㅓ彐"
    },
    {
        "original": "야곡",
        "transformed": "눈ㅕㅇ"
    },
    {
        "original": "공기놀이",
        "transformed": "ㅣㅇ룩ㅣㄴ운"
    },
    {
        "original": "농아사",
        "transformed": "ㅓVㅓㅇ욱"
    },
    {
        "original": "옥매",
        "transformed": "ㅐㅁ눙"
    },
    {
        "original": "농기계",
        "transformed": "ㅣㅑㄴㅣㄴ욱"
    },
    {
        "original": "공해",
        "transformed": "ㅐ우운"
    },
    {
        "original": "풍세",
        "transformed": "ㅣㅏV옾"
    },
    {
        "original": "골자",
        "transformed": "ㅓと룬"
    },
    {
        "original": "올겨울",
        "transformed": "롱ㅑㄴ룽"
    },
    {
        "original": "여군",
        "transformed": "곤ㅑㅇ"
    },
    {
        "original": "내용골",
        "transformed": "룬융ㅐㄱ"
    },
    {
        "original": "논마지기",
        "transformed": "ㅣㄴㅣとㅓㅁ국"
    },
    {
        "original": "공이",
        "transformed": "ㅣㅇ운"
    },
    {
        "original": "싸움터",
        "transformed": "ㅏ彐몽ㅓW"
    },
    {
        "original": "어공",
        "transformed": "운ㅏㅇ"
    },
    {
        "original": "내자물거",
        "transformed": "ㅏㄴ롬ㅓとㅐㄱ"
    },
    {
        "original": "네눈이",
        "transformed": "ㅣㅇ곡ㅣㅏㄱ"
    },
    {
        "original": "가시눈",
        "transformed": "곡ㅣVㅓㄴ"
    },
    {
        "original": "골패기",
        "transformed": "ㅣㄴㅐㅍ룬"
    },
    {
        "original": "운거",
        "transformed": "ㅏㄴ공"
    },
    {
        "original": "궁자",
        "transformed": "ㅓと온"
    },
    {
        "original": "기공",
        "transformed": "운ㅣㄴ"
    },
    {
        "original": "어깨높이",
        "transformed": "ㅣㅇ푹ㅐㄴㄴㅏㅇ"
    },
    {
        "original": "그물배",
        "transformed": "ㅐA롬匸"
    },
    {
        "original": "문계",
        "transformed": "ㅣㅑㄴ곰"
    },
    {
        "original": "어공어사",
        "transformed": "ㅓVㅏㅇ운ㅏㅇ"
    },
    {
        "original": "목가래",
        "transformed": "ㅐㄹㅓㄴ눔"
    },
    {
        "original": "다목다리",
        "transformed": "ㅣㄹㅓ그눔ㅓ그"
    },
    {
        "original": "떼몰이",
        "transformed": "ㅣㅇ룸ㅣㅏ그그"
    },
    {
        "original": "나문재",
        "transformed": "ㅐと곰ㅓㄱ"
    },
    {
        "original": "제비물떼새",
        "transformed": "ㅐVㅣㅏ그그롬ㅣAㅣㅏと"
    },
    {
        "original": "대용재",
        "transformed": "ㅐと융ㅐ그"
    },
    {
        "original": "내사옥",
        "transformed": "눙ㅓVㅐㄱ"
    },
    {
        "original": "묵서",
        "transformed": "ㅏV놈"
    },
    {
        "original": "골계미",
        "transformed": "ㅣㅁㅣㅑㄴ룬"
    },
    {
        "original": "녹대",
        "transformed": "ㅐ그눅"
    },
    {
        "original": "예문가",
        "transformed": "ㅓㄴ곰ㅣㅑㅇ"
    },
    {
        "original": "문세",
        "transformed": "ㅣㅏV곰"
    },
    {
        "original": "몽가리내",
        "transformed": "ㅐㄱㅣㄹㅓㄴ움"
    },
    {
        "original": "티눈",
        "transformed": "곡ㅣ彐"
    },
    {
        "original": "몸때",
        "transformed": "ㅐ그그뭄"
    },
    {
        "original": "공개",
        "transformed": "ㅐㄴ운"
    },
    {
        "original": "지군",
        "transformed": "곤ㅣと"
    },
    {
        "original": "웅비",
        "transformed": "ㅣA옹"
    },
    {
        "original": "세농가",
        "transformed": "ㅓㄴ욱ㅣㅏV"
    },
    {
        "original": "문사",
        "transformed": "ㅓV곰"
    },
    {
        "original": "지대공",
        "transformed": "운ㅐ그ㅣと"
    },
    {
        "original": "농기패",
        "transformed": "ㅐㅍㅣㄴ욱"
    },
    {
        "original": "허욕",
        "transformed": "늉ㅏ우"
    },
    {
        "original": "매온",
        "transformed": "궁ㅐㅁ"
    },
    {
        "original": "목제",
        "transformed": "ㅣㅏと눔"
    },
    {
        "original": "야풍",
        "transformed": "옾ㅕㅇ"
    },
    {
        "original": "용해제",
        "transformed": "ㅣㅏとㅐ우융"
    },
    {
        "original": "목나사",
        "transformed": "ㅓVㅓㄱ눔"
    },
    {
        "original": "계옥지지",
        "transformed": "ㅣとㅣと눙ㅣㅑㄴ"
    },
    {
        "original": "물리개",
        "transformed": "ㅐㄴㅣㄹ롬"
    },
    {
        "original": "녹비",
        "transformed": "ㅣA눅"
    },
    {
        "original": "해군",
        "transformed": "곤ㅐ우"
    },
    {
        "original": "목공예",
        "transformed": "ㅣㅑㅇ운눔"
    },
    {
        "original": "공가",
        "transformed": "ㅓㄴ운"
    },
    {
        "original": "패운",
        "transformed": "공ㅐㅍ"
    },
    {
        "original": "목피리재비",
        "transformed": "ㅣAㅐとㅣㄹㅣㅍ눔"
    },
    {
        "original": "대공세",
        "transformed": "ㅣㅏV운ㅐ그"
    },
    {
        "original": "세곡",
        "transformed": "눈ㅣㅏV"
    },
    {
        "original": "묵기",
        "transformed": "ㅣㄴ놈"
    },
    {
        "original": "재시공",
        "transformed": "운ㅣVㅐと"
    },
    {
        "original": "지골",
        "transformed": "룬ㅣと"
    },
    {
        "original": "미네굴",
        "transformed": "론ㅣㅏㄱㅣㅁ"
    },
    {
        "original": "하농",
        "transformed": "욱ㅓ우"
    },
    {
        "original": "문서대",
        "transformed": "ㅐ그ㅏV곰"
    },
    {
        "original": "기사궁",
        "transformed": "온ㅓVㅣㄴ"
    },
    {
        "original": "해묵",
        "transformed": "놈ㅐ우"
    },
    {
        "original": "물떼기",
        "transformed": "ㅣㄴㅣㅏ그그롬"
    },
    {
        "original": "재물대",
        "transformed": "ㅐ그롬ㅐと"
    },
    {
        "original": "올배",
        "transformed": "ㅐA룽"
    },
    {
        "original": "용자례",
        "transformed": "ㅣㅑㄹㅓと융"
    },
    {
        "original": "비옹",
        "transformed": "웅ㅣA"
    },
    {
        "original": "내비리국",
        "transformed": "논ㅣㄹㅣAㅐㄱ"
    },
    {
        "original": "곡해",
        "transformed": "ㅐ우눈"
    },
    {
        "original": "공리욕",
        "transformed": "늉ㅣㄹ운"
    },
    {
        "original": "궁해",
        "transformed": "ㅐ우온"
    },
    {
        "original": "피목",
        "transformed": "눔ㅣㅍ"
    },
    {
        "original": "재품",
        "transformed": "뫂ㅐと"
    },
    {
        "original": "기계제품",
        "transformed": "뫂ㅣㅏとㅣㅑㄴㅣㄴ"
    },
    {
        "original": "농지",
        "transformed": "ㅣと욱"
    },
    {
        "original": "온혜",
        "transformed": "ㅣㅑ우궁"
    },
    {
        "original": "비계공",
        "transformed": "운ㅣㅑㄴㅣA"
    },
    {
        "original": "비폭",
        "transformed": "눞ㅣA"
    },
    {
        "original": "세골",
        "transformed": "룬ㅣㅏV"
    },
    {
        "original": "군계",
        "transformed": "ㅣㅑㄴ곤"
    },
    {
        "original": "계농",
        "transformed": "욱ㅣㅑㄴ"
    },
    {
        "original": "해운",
        "transformed": "공ㅐ우"
    },
    {
        "original": "이운",
        "transformed": "공ㅣㅇ"
    },
    {
        "original": "대풍",
        "transformed": "옾ㅐ그"
    },
    {
        "original": "몰지",
        "transformed": "ㅣと룸"
    },
    {
        "original": "폭배",
        "transformed": "ㅐA눞"
    },
    {
        "original": "새눈",
        "transformed": "곡ㅐV"
    },
    {
        "original": "여래비리국",
        "transformed": "논ㅣㄹㅣAㅐㄹㅑㅇ"
    },
    {
        "original": "새물내",
        "transformed": "ㅐㄱ롬ㅐV"
    },
    {
        "original": "비매품",
        "transformed": "뫂ㅐㅁㅣA"
    },
    {
        "original": "그물메기",
        "transformed": "ㅣㄴㅣㅏㅁ롬匸"
    },
    {
        "original": "미온계",
        "transformed": "ㅣㅑㄴ궁ㅣㅁ"
    },
    {
        "original": "풍개",
        "transformed": "ㅐㄴ옾"
    },
    {
        "original": "목례",
        "transformed": "ㅣㅑㄹ눔"
    },
    {
        "original": "사농",
        "transformed": "욱ㅓV"
    },
    {
        "original": "굴때",
        "transformed": "ㅐ그그론"
    },
    {
        "original": "나국",
        "transformed": "논ㅓㄱ"
    },
    {
        "original": "내궁",
        "transformed": "온ㅐㄱ"
    },
    {
        "original": "높새",
        "transformed": "ㅐV푹"
    },
    {
        "original": "개풍",
        "transformed": "옾ㅐㄴ"
    },
    {
        "original": "논파",
        "transformed": "ㅓㅍ국"
    },
    {
        "original": "대새풀",
        "transformed": "롶ㅐVㅐ그"
    },
    {
        "original": "품새",
        "transformed": "ㅐV뫂"
    },
    {
        "original": "문이지지",
        "transformed": "ㅣとㅣとㅣㅇ곰"
    },
    {
        "original": "용서",
        "transformed": "ㅏV융"
    },
    {
        "original": "싸움배",
        "transformed": "ㅐA몽ㅓW"
    },
    {
        "original": "이공계",
        "transformed": "ㅣㅑㄴ운ㅣㅇ"
    },
    {
        "original": "풀매기",
        "transformed": "ㅣㄴㅐㅁ롶"
    },
    {
        "original": "애용물",
        "transformed": "롬융ㅐㅇ"
    },
    {
        "original": "배농",
        "transformed": "욱ㅐA"
    },
    {
        "original": "나문재나물",
        "transformed": "롬ㅓㄱㅐと곰ㅓㄱ"
    },
    {
        "original": "눅지배기",
        "transformed": "ㅣㄴㅐAㅣと녹"
    },
    {
        "original": "옥해",
        "transformed": "ㅐ우눙"
    },
    {
        "original": "타옥",
        "transformed": "눙ㅓ彐"
    },
    {
        "original": "문배",
        "transformed": "ㅐA곰"
    },
    {
        "original": "제풍",
        "transformed": "옾ㅣㅏと"
    },
    {
        "original": "문군사",
        "transformed": "ㅓV곤곰"
    },
    {
        "original": "매국",
        "transformed": "논ㅐㅁ"
    },
    {
        "original": "푼거리",
        "transformed": "ㅣㄹㅏㄴ곺"
    },
    {
        "original": "이풍",
        "transformed": "옾ㅣㅇ"
    },
    {
        "original": "배공",
        "transformed": "운ㅐA"
    },
    {
        "original": "논벼",
        "transformed": "ㅑA국"
    },
    {
        "original": "제문",
        "transformed": "곰ㅣㅏと"
    },
    {
        "original": "태사공",
        "transformed": "운ㅓVㅐ彐"
    },
    {
        "original": "나농",
        "transformed": "욱ㅓㄱ"
    },
    {
        "original": "계운",
        "transformed": "공ㅣㅑㄴ"
    },
    {
        "original": "기폭제",
        "transformed": "ㅣㅏと눞ㅣㄴ"
    },
    {
        "original": "운혜",
        "transformed": "ㅣㅑ우공"
    },
    {
        "original": "계곡풍",
        "transformed": "옾눈ㅣㅑㄴ"
    },
    {
        "original": "곤시",
        "transformed": "ㅣV군"
    },
    {
        "original": "서곡",
        "transformed": "눈ㅏV"
    },
    {
        "original": "가야국",
        "transformed": "논ㅕㅇㅓㄴ"
    },
    {
        "original": "몰이해",
        "transformed": "ㅐ우ㅣㅇ룸"
    },
    {
        "original": "공기비",
        "transformed": "ㅣAㅣㄴ운"
    },
    {
        "original": "문야",
        "transformed": "ㅕㅇ곰"
    },
    {
        "original": "품자리",
        "transformed": "ㅣㄹㅓと뫂"
    },
    {
        "original": "굴개",
        "transformed": "ㅐㄴ론"
    },
    {
        "original": "미개국",
        "transformed": "논ㅐㄴㅣㅁ"
    },
    {
        "original": "어옹",
        "transformed": "웅ㅏㅇ"
    },
    {
        "original": "미군",
        "transformed": "곤ㅣㅁ"
    },
    {
        "original": "재운",
        "transformed": "공ㅐと"
    },
    {
        "original": "배사문",
        "transformed": "곰ㅓVㅐA"
    },
    {
        "original": "나문재기",
        "transformed": "ㅣㄴㅐと곰ㅓㄱ"
    },
    {
        "original": "내온",
        "transformed": "궁ㅐㄱ"
    },
    {
        "original": "녹야",
        "transformed": "ㅕㅇ눅"
    },
    {
        "original": "그물자리",
        "transformed": "ㅣㄹㅓと롬匸"
    },
    {
        "original": "혜군",
        "transformed": "곤ㅣㅑ우"
    },
    {
        "original": "목대",
        "transformed": "ㅐ그눔"
    },
    {
        "original": "골자래",
        "transformed": "ㅐㄹㅓと룬"
    },
    {
        "original": "미저골",
        "transformed": "룬ㅏとㅣㅁ"
    },
    {
        "original": "미제품",
        "transformed": "뫂ㅣㅏとㅣㅁ"
    },
    {
        "original": "풀거미",
        "transformed": "ㅣㅁㅏㄴ롶"
    },
    {
        "original": "골씨",
        "transformed": "ㅣW룬"
    },
    {
        "original": "지태사국사",
        "transformed": "ㅓV논ㅓVㅐ彐ㅣと"
    },
    {
        "original": "울거미",
        "transformed": "ㅣㅁㅏㄴ롱"
    },
    {
        "original": "국세",
        "transformed": "ㅣㅏV논"
    },
    {
        "original": "목야",
        "transformed": "ㅕㅇ눔"
    },
    {
        "original": "궁내",
        "transformed": "ㅐㄱ온"
    },
    {
        "original": "깨풀",
        "transformed": "롶ㅐㄴㄴ"
    },
    {
        "original": "해저곡",
        "transformed": "눈ㅏとㅐ우"
    },
    {
        "original": "놀래기",
        "transformed": "ㅣㄴㅐㄹ룩"
    },
    {
        "original": "께묵",
        "transformed": "놈ㅣㅏㄴㄴ"
    },
    {
        "original": "태궁",
        "transformed": "온ㅐ彐"
    },
    {
        "original": "기공국",
        "transformed": "논운ㅣㄴ"
    },
    {
        "original": "비미국",
        "transformed": "논ㅣㅁㅣA"
    },
    {
        "original": "문예가",
        "transformed": "ㅓㄴㅣㅑㅇ곰"
    },
    {
        "original": "몸티",
        "transformed": "ㅣ彐뭄"
    },
    {
        "original": "푼내기",
        "transformed": "ㅣㄴㅐㄱ곺"
    },
    {
        "original": "옥예",
        "transformed": "ㅣㅑㅇ눙"
    },
    {
        "original": "물씨",
        "transformed": "ㅣW롬"
    },
    {
        "original": "재궁",
        "transformed": "온ㅐと"
    },
    {
        "original": "비계목",
        "transformed": "눔ㅣㅑㄴㅣA"
    },
    {
        "original": "시재문",
        "transformed": "곰ㅐとㅣV"
    },
    {
        "original": "문제사",
        "transformed": "ㅓVㅣㅏと곰"
    },
    {
        "original": "대자재궁",
        "transformed": "온ㅐとㅓとㅐ그"
    },
    {
        "original": "매개물",
        "transformed": "롬ㅐㄴㅐㅁ"
    },
    {
        "original": "올빼미",
        "transformed": "ㅣㅁㅐAA룽"
    },
    {
        "original": "목자놀이",
        "transformed": "ㅣㅇ룩ㅓと눔"
    },
    {
        "original": "애국가",
        "transformed": "ㅓㄴ논ㅐㅇ"
    },
    {
        "original": "비운문",
        "transformed": "곰공ㅣA"
    },
    {
        "original": "재공품",
        "transformed": "뫂운ㅐと"
    },
    {
        "original": "가군",
        "transformed": "곤ㅓㄴ"
    },
    {
        "original": "문피",
        "transformed": "ㅣㅍ곰"
    },
    {
        "original": "대군물",
        "transformed": "롬곤ㅐ그"
    },
    {
        "original": "까풀",
        "transformed": "롶ㅓㄴㄴ"
    },
    {
        "original": "가래그물",
        "transformed": "롬匸ㅐㄹㅓㄴ"
    },
    {
        "original": "서풍",
        "transformed": "옾ㅏV"
    },
    {
        "original": "풍사",
        "transformed": "ㅓV옾"
    },
    {
        "original": "개묵새",
        "transformed": "ㅐV놈ㅐㄴ"
    },
    {
        "original": "군대",
        "transformed": "ㅐ그곤"
    },
    {
        "original": "골다리",
        "transformed": "ㅣㄹㅓ그룬"
    },
    {
        "original": "묵례",
        "transformed": "ㅣㅑㄹ놈"
    },
    {
        "original": "물리계",
        "transformed": "ㅣㅑㄴㅣㄹ롬"
    },
    {
        "original": "지문",
        "transformed": "곰ㅣと"
    },
    {
        "original": "올풀이",
        "transformed": "ㅣㅇ롶룽"
    },
    {
        "original": "패목",
        "transformed": "눔ㅐㅍ"
    },
    {
        "original": "재물",
        "transformed": "롬ㅐと"
    },
    {
        "original": "웅재",
        "transformed": "ㅐと옹"
    },
    {
        "original": "온재",
        "transformed": "ㅐと궁"
    },
    {
        "original": "녹미",
        "transformed": "ㅣㅁ눅"
    },
    {
        "original": "기울기자",
        "transformed": "ㅓとㅣㄴ롱ㅣㄴ"
    },
    {
        "original": "눈매",
        "transformed": "ㅐㅁ곡"
    },
    {
        "original": "기해사옥",
        "transformed": "눙ㅓVㅐ우ㅣㄴ"
    },
    {
        "original": "이목지사",
        "transformed": "ㅓVㅣと눔ㅣㅇ"
    },
    {
        "original": "옴게",
        "transformed": "ㅣㅏㄴ뭉"
    },
    {
        "original": "농제",
        "transformed": "ㅣㅏと욱"
    },
    {
        "original": "용제",
        "transformed": "ㅣㅏと융"
    },
    {
        "original": "물레나물",
        "transformed": "롬ㅓㄱㅣㅏㄹ롬"
    },
    {
        "original": "자용",
        "transformed": "융ㅓと"
    },
    {
        "original": "문예사",
        "transformed": "ㅓVㅣㅑㅇ곰"
    },
    {
        "original": "국재",
        "transformed": "ㅐと논"
    },
    {
        "original": "문내",
        "transformed": "ㅐㄱ곰"
    },
    {
        "original": "미몽",
        "transformed": "움ㅣㅁ"
    },
    {
        "original": "세공마",
        "transformed": "ㅓㅁ운ㅣㅏV"
    },
    {
        "original": "하곡",
        "transformed": "눈ㅓ우"
    },
    {
        "original": "거풀",
        "transformed": "롶ㅏㄴ"
    },
    {
        "original": "애놈",
        "transformed": "묵ㅐㅇ"
    },
    {
        "original": "세농",
        "transformed": "욱ㅣㅏV"
    },
    {
        "original": "국가",
        "transformed": "ㅓㄴ논"
    },
    {
        "original": "아궁이",
        "transformed": "ㅣㅇ온ㅓㅇ"
    },
    {
        "original": "물바가지",
        "transformed": "ㅣとㅓㄴㅓA롬"
    },
    {
        "original": "목마패",
        "transformed": "ㅐㅍㅓㅁ눔"
    },
    {
        "original": "문래",
        "transformed": "ㅐㄹ곰"
    },
    {
        "original": "몸가눔",
        "transformed": "목ㅓㄴ뭄"
    },
    {
        "original": "용기",
        "transformed": "ㅣㄴ융"
    },
    {
        "original": "파군",
        "transformed": "곤ㅓㅍ"
    },
    {
        "original": "시품",
        "transformed": "뫂ㅣV"
    },
    {
        "original": "사세국",
        "transformed": "논ㅣㅏVㅓV"
    },
    {
        "original": "운야",
        "transformed": "ㅕㅇ공"
    },
    {
        "original": "파라나국",
        "transformed": "논ㅓㄱㅓㄹㅓㅍ"
    },
    {
        "original": "웅어",
        "transformed": "ㅏㅇ옹"
    },
    {
        "original": "풀머리",
        "transformed": "ㅣㄹㅏㅁ롶"
    },
    {
        "original": "제사공",
        "transformed": "운ㅓVㅣㅏと"
    },
    {
        "original": "궁계",
        "transformed": "ㅣㅑㄴ온"
    },
    {
        "original": "재용",
        "transformed": "융ㅐと"
    },
    {
        "original": "내용품",
        "transformed": "뫂융ㅐㄱ"
    },
    {
        "original": "가공품",
        "transformed": "뫂운ㅓㄴ"
    },
    {
        "original": "가려움",
        "transformed": "몽ㅑㄹㅓㄴ"
    },
    {
        "original": "기운",
        "transformed": "공ㅣㄴ"
    },
    {
        "original": "여풍",
        "transformed": "옾ㅑㅇ"
    },
    {
        "original": "새궁",
        "transformed": "온ㅐV"
    },
    {
        "original": "해용",
        "transformed": "융ㅐ우"
    },
    {
        "original": "국기배례",
        "transformed": "ㅣㅑㄹㅐAㅣㄴ논"
    },
    {
        "original": "시웅",
        "transformed": "옹ㅣV"
    },
    {
        "original": "가풍",
        "transformed": "옾ㅓㄴ"
    },
    {
        "original": "올가미",
        "transformed": "ㅣㅁㅓㄴ룽"
    },
    {
        "original": "옥하가옥",
        "transformed": "눙ㅓㄴㅓ우눙"
    },
    {
        "original": "몽사",
        "transformed": "ㅓV움"
    },
    {
        "original": "물개",
        "transformed": "ㅐㄴ롬"
    },
    {
        "original": "미궁",
        "transformed": "온ㅣㅁ"
    },
    {
        "original": "세풍",
        "transformed": "옾ㅣㅏV"
    },
    {
        "original": "군재",
        "transformed": "ㅐと곤"
    },
    {
        "original": "가지굴",
        "transformed": "론ㅣとㅓㄴ"
    },
    {
        "original": "나비눈",
        "transformed": "곡ㅣAㅓㄱ"
    },
    {
        "original": "몰자비",
        "transformed": "ㅣAㅓと룸"
    },
    {
        "original": "개욕패",
        "transformed": "ㅐㅍ늉ㅐㄴ"
    },
    {
        "original": "곡다",
        "transformed": "ㅓ그눈"
    },
    {
        "original": "내목",
        "transformed": "눔ㅐㄱ"
    },
    {
        "original": "개폐문",
        "transformed": "곰ㅣㅑㅍㅐㄴ"
    },
    {
        "original": "물지게",
        "transformed": "ㅣㅏㄴㅣと롬"
    },
    {
        "original": "국계",
        "transformed": "ㅣㅑㄴ논"
    },
    {
        "original": "곡타",
        "transformed": "ㅓ彐눈"
    },
    {
        "original": "사리풀",
        "transformed": "롶ㅣㄹㅓV"
    },
    {
        "original": "풀베개",
        "transformed": "ㅐㄴㅣㅏA롶"
    },
    {
        "original": "게목나물",
        "transformed": "롬ㅓㄱ눔ㅣㅏㄴ"
    },
    {
        "original": "물메기",
        "transformed": "ㅣㄴㅣㅏㅁ롬"
    },
    {
        "original": "움베",
        "transformed": "ㅣㅏA몽"
    },
    {
        "original": "개여울",
        "transformed": "롱ㅑㅇㅐㄴ"
    },
    {
        "original": "제국",
        "transformed": "논ㅣㅏと"
    },
    {
        "original": "목가시",
        "transformed": "ㅣVㅓㄴ눔"
    },
    {
        "original": "배해문",
        "transformed": "곰ㅐ우ㅐA"
    },
    {
        "original": "해몽",
        "transformed": "움ㅐ우"
    },
    {
        "original": "패용",
        "transformed": "융ㅐㅍ"
    },
    {
        "original": "목려",
        "transformed": "ㅑㄹ눔"
    },
    {
        "original": "묵사리",
        "transformed": "ㅣㄹㅓV놈"
    },
    {
        "original": "대국자",
        "transformed": "ㅓと논ㅐ그"
    },
    {
        "original": "물품세",
        "transformed": "ㅣㅏV뫂롬"
    },
    {
        "original": "제운기",
        "transformed": "ㅣㄴ공ㅣㅏと"
    },
    {
        "original": "자궁문",
        "transformed": "곰온ㅓと"
    },
    {
        "original": "개풍군",
        "transformed": "곤옾ㅐㄴ"
    },
    {
        "original": "계몽기",
        "transformed": "ㅣㄴ움ㅣㅑㄴ"
    },
    {
        "original": "예궁",
        "transformed": "온ㅣㅑㅇ"
    },
    {
        "original": "공여",
        "transformed": "ㅑㅇ운"
    },
    {
        "original": "궁예",
        "transformed": "ㅣㅑㅇ온"
    },
    {
        "original": "내용물",
        "transformed": "롬융ㅐㄱ"
    },
    {
        "original": "머리풀매기",
        "transformed": "ㅣㄴㅐㅁ롶ㅣㄹㅏㅁ"
    },
    {
        "original": "물풀매",
        "transformed": "ㅐㅁ롶롬"
    },
    {
        "original": "물띠",
        "transformed": "ㅣ그그롬"
    },
    {
        "original": "공문서",
        "transformed": "ㅏV곰운"
    },
    {
        "original": "곡물세",
        "transformed": "ㅣㅏV롬눈"
    },
    {
        "original": "여운",
        "transformed": "공ㅑㅇ"
    },
    {
        "original": "사사국",
        "transformed": "논ㅓVㅓV"
    },
    {
        "original": "공제",
        "transformed": "ㅣㅏと운"
    },
    {
        "original": "미곡",
        "transformed": "눈ㅣㅁ"
    },
    {
        "original": "개울가",
        "transformed": "ㅓㄴ롱ㅐㄴ"
    },
    {
        "original": "목사아지",
        "transformed": "ㅣとㅓㅇㅓV눔"
    },
    {
        "original": "파리옥",
        "transformed": "눙ㅣㄹㅓㅍ"
    },
    {
        "original": "뼈품",
        "transformed": "뫂ㅑAA"
    },
    {
        "original": "용라",
        "transformed": "ㅓㄹ융"
    },
    {
        "original": "새개골",
        "transformed": "룬ㅐㄴㅐV"
    },
    {
        "original": "공문제",
        "transformed": "ㅣㅏと곰운"
    },
    {
        "original": "골마지",
        "transformed": "ㅣとㅓㅁ룬"
    },
    {
        "original": "서푼",
        "transformed": "곺ㅏV"
    },
    {
        "original": "겨풀",
        "transformed": "롶ㅑㄴ"
    },
    {
        "original": "자문",
        "transformed": "곰ㅓと"
    },
    {
        "original": "곡거",
        "transformed": "ㅏㄴ눈"
    },
    {
        "original": "목미레",
        "transformed": "ㅣㅏㄹㅣㅁ눔"
    },
    {
        "original": "해골",
        "transformed": "룬ㅐ우"
    },
    {
        "original": "대용",
        "transformed": "융ㅐ그"
    },
    {
        "original": "공공용지",
        "transformed": "ㅣと융운운"
    },
    {
        "original": "군사물",
        "transformed": "롬ㅓV곤"
    },
    {
        "original": "기미국",
        "transformed": "논ㅣㅁㅣㄴ"
    },
    {
        "original": "욕례",
        "transformed": "ㅣㅑㄹ늉"
    },
    {
        "original": "문패",
        "transformed": "ㅐㅍ곰"
    },
    {
        "original": "나물",
        "transformed": "롬ㅓㄱ"
    },
    {
        "original": "계옹",
        "transformed": "웅ㅣㅑㄴ"
    },
    {
        "original": "물까매그",
        "transformed": "匸ㅐㅁㅓㄴㄴ롬"
    },
    {
        "original": "새물",
        "transformed": "롬ㅐV"
    },
    {
        "original": "계피문",
        "transformed": "곰ㅣㅍㅣㅑㄴ"
    },
    {
        "original": "저묵",
        "transformed": "놈ㅏと"
    },
    {
        "original": "애운",
        "transformed": "공ㅐㅇ"
    },
    {
        "original": "태옥",
        "transformed": "눙ㅐ彐"
    },
    {
        "original": "애옥",
        "transformed": "눙ㅐㅇ"
    },
    {
        "original": "파재목",
        "transformed": "눔ㅐとㅓㅍ"
    },
    {
        "original": "기국다",
        "transformed": "ㅓ그논ㅣㄴ"
    },
    {
        "original": "제공",
        "transformed": "운ㅣㅏと"
    },
    {
        "original": "자품",
        "transformed": "뫂ㅓと"
    },
    {
        "original": "녹해",
        "transformed": "ㅐ우눅"
    },
    {
        "original": "군거",
        "transformed": "ㅏㄴ곤"
    },
    {
        "original": "재울",
        "transformed": "롱ㅐと"
    },
    {
        "original": "예국",
        "transformed": "논ㅣㅑㅇ"
    },
    {
        "original": "기몽",
        "transformed": "움ㅣㄴ"
    },
    {
        "original": "곡재아",
        "transformed": "ㅓㅇㅐと눈"
    },
    {
        "original": "자목지재",
        "transformed": "ㅐとㅣと눔ㅓと"
    },
    {
        "original": "군사비",
        "transformed": "ㅣAㅓV곤"
    },
    {
        "original": "제골",
        "transformed": "룬ㅣㅏと"
    },
    {
        "original": "풍계",
        "transformed": "ㅣㅑㄴ옾"
    },
    {
        "original": "게목",
        "transformed": "눔ㅣㅏㄴ"
    },
    {
        "original": "계문",
        "transformed": "곰ㅣㅑㄴ"
    },
    {
        "original": "서울애기",
        "transformed": "ㅣㄴㅐㅇ롱ㅏV"
    },
    {
        "original": "개굴때기",
        "transformed": "ㅣㄴㅐ그그론ㅐㄴ"
    },
    {
        "original": "욕해",
        "transformed": "ㅐ우늉"
    },
    {
        "original": "눈비",
        "transformed": "ㅣA곡"
    },
    {
        "original": "눈물비",
        "transformed": "ㅣA롬곡"
    },
    {
        "original": "풀베기",
        "transformed": "ㅣㄴㅣㅏA롶"
    },
    {
        "original": "사내놈",
        "transformed": "묵ㅐㄱㅓV"
    },
    {
        "original": "애기풀",
        "transformed": "롶ㅣㄴㅐㅇ"
    },
    {
        "original": "겨울나기",
        "transformed": "ㅣㄴㅓㄱ롱ㅑㄴ"
    },
    {
        "original": "계공",
        "transformed": "운ㅣㅑㄴ"
    },
    {
        "original": "미려골",
        "transformed": "룬ㅑㄹㅣㅁ"
    },
    {
        "original": "계곡미",
        "transformed": "ㅣㅁ눈ㅣㅑㄴ"
    },
    {
        "original": "다리품",
        "transformed": "뫂ㅣㄹㅓ그"
    },
    {
        "original": "물매미",
        "transformed": "ㅣㅁㅐㅁ롬"
    },
    {
        "original": "해옥",
        "transformed": "눙ㅐ우"
    },
    {
        "original": "온기",
        "transformed": "ㅣㄴ궁"
    },
    {
        "original": "눈겨눔",
        "transformed": "목ㅑㄴ곡"
    },
    {
        "original": "문제시",
        "transformed": "ㅣVㅣㅏと곰"
    },
    {
        "original": "사데풀",
        "transformed": "롶ㅣㅏ그ㅓV"
    },
    {
        "original": "이제공",
        "transformed": "운ㅣㅏとㅣㅇ"
    },
    {
        "original": "논지",
        "transformed": "ㅣと국"
    },
    {
        "original": "지옥세계",
        "transformed": "ㅣㅑㄴㅣㅏV눙ㅣと"
    },
    {
        "original": "사품",
        "transformed": "뫂ㅓV"
    },
    {
        "original": "세목",
        "transformed": "눔ㅣㅏV"
    },
    {
        "original": "곡개",
        "transformed": "ㅐㄴ눈"
    },
    {
        "original": "묵자",
        "transformed": "ㅓと놈"
    },
    {
        "original": "품바",
        "transformed": "ㅓA뫂"
    },
    {
        "original": "이국",
        "transformed": "논ㅣㅇ"
    },
    {
        "original": "사지골",
        "transformed": "룬ㅣとㅓV"
    },
    {
        "original": "거리풀이",
        "transformed": "ㅣㅇ롶ㅣㄹㅏㄴ"
    },
    {
        "original": "궁이배",
        "transformed": "ㅐAㅣㅇ온"
    },
    {
        "original": "제폭",
        "transformed": "눞ㅣㅏと"
    },
    {
        "original": "군기",
        "transformed": "ㅣㄴ곤"
    },
    {
        "original": "국새",
        "transformed": "ㅐV논"
    },
    {
        "original": "골지",
        "transformed": "ㅣと룬"
    },
    {
        "original": "하마온",
        "transformed": "궁ㅓㅁㅓ우"
    },
    {
        "original": "녹기",
        "transformed": "ㅣㄴ눅"
    },
    {
        "original": "곡재피",
        "transformed": "ㅣㅍㅐと눈"
    },
    {
        "original": "용지",
        "transformed": "ㅣと융"
    },
    {
        "original": "군사용",
        "transformed": "융ㅓV곤"
    },
    {
        "original": "피눈물",
        "transformed": "롬곡ㅣㅍ"
    },
    {
        "original": "가새풀",
        "transformed": "롶ㅐVㅓㄴ"
    },
    {
        "original": "눈시울",
        "transformed": "롱ㅣV곡"
    },
    {
        "original": "물혜",
        "transformed": "ㅣㅑ우롬"
    },
    {
        "original": "군자곡",
        "transformed": "눈ㅓと곤"
    },
    {
        "original": "몽혜",
        "transformed": "ㅣㅑ우움"
    },
    {
        "original": "논가",
        "transformed": "ㅓㄴ국"
    },
    {
        "original": "하지골",
        "transformed": "룬ㅣとㅓ우"
    },
    {
        "original": "자공",
        "transformed": "운ㅓと"
    },
    {
        "original": "목제품",
        "transformed": "뫂ㅣㅏと눔"
    },
    {
        "original": "다비문",
        "transformed": "곰ㅣAㅓ그"
    },
    {
        "original": "폐물",
        "transformed": "롬ㅣㅑㅍ"
    },
    {
        "original": "골제품",
        "transformed": "뫂ㅣㅏと룬"
    },
    {
        "original": "마묵",
        "transformed": "놈ㅓㅁ"
    },
    {
        "original": "욕제",
        "transformed": "ㅣㅏと늉"
    },
    {
        "original": "폐품",
        "transformed": "뫂ㅣㅑㅍ"
    },
    {
        "original": "목매아지",
        "transformed": "ㅣとㅓㅇㅐㅁ눔"
    },
    {
        "original": "공리계",
        "transformed": "ㅣㅑㄴㅣㄹ운"
    },
    {
        "original": "피폭",
        "transformed": "눞ㅣㅍ"
    },
    {
        "original": "물이끼",
        "transformed": "ㅣㄴㄴㅣㅇ롬"
    },
    {
        "original": "자국눈",
        "transformed": "곡논ㅓと"
    },
    {
        "original": "어레미논",
        "transformed": "국ㅣㅁㅣㅏㄹㅏㅇ"
    },
    {
        "original": "비굴",
        "transformed": "론ㅣA"
    },
    {
        "original": "사국",
        "transformed": "논ㅓV"
    },
    {
        "original": "허울",
        "transformed": "롱ㅏ우"
    },
    {
        "original": "가마목",
        "transformed": "눔ㅓㅁㅓㄴ"
    },
    {
        "original": "배움터",
        "transformed": "ㅏ彐몽ㅐA"
    },
    {
        "original": "물떼새",
        "transformed": "ㅐVㅣㅏ그그롬"
    },
    {
        "original": "울폐",
        "transformed": "ㅣㅑㅍ롱"
    },
    {
        "original": "내용",
        "transformed": "융ㅐㄱ"
    },
    {
        "original": "애곡",
        "transformed": "눈ㅐㅇ"
    },
    {
        "original": "나목",
        "transformed": "눔ㅓㄱ"
    },
    {
        "original": "여문",
        "transformed": "곰ㅑㅇ"
    },
    {
        "original": "운저",
        "transformed": "ㅏと공"
    },
    {
        "original": "옹다리",
        "transformed": "ㅣㄹㅓ그웅"
    },
    {
        "original": "군티",
        "transformed": "ㅣ彐곤"
    },
    {
        "original": "웅피",
        "transformed": "ㅣㅍ옹"
    },
    {
        "original": "녹계",
        "transformed": "ㅣㅑㄴ눅"
    },
    {
        "original": "용거",
        "transformed": "ㅏㄴ융"
    },
    {
        "original": "옥패",
        "transformed": "ㅐㅍ눙"
    },
    {
        "original": "골재",
        "transformed": "ㅐと룬"
    },
    {
        "original": "목계",
        "transformed": "ㅣㅑㄴ눔"
    },
    {
        "original": "태풍목",
        "transformed": "눔옾ㅐ彐"
    },
    {
        "original": "시공자",
        "transformed": "ㅓと운ㅣV"
    },
    {
        "original": "올새",
        "transformed": "ㅐV룽"
    },
    {
        "original": "풍목지비",
        "transformed": "ㅣAㅣと눔옾"
    },
    {
        "original": "눈나비",
        "transformed": "ㅣAㅓㄱ곡"
    },
    {
        "original": "목다리",
        "transformed": "ㅣㄹㅓ그눔"
    },
    {
        "original": "옥서",
        "transformed": "ㅏV눙"
    },
    {
        "original": "국자",
        "transformed": "ㅓと논"
    },
    {
        "original": "올깨미",
        "transformed": "ㅣㅁㅐㄴㄴ룽"
    },
    {
        "original": "국제",
        "transformed": "ㅣㅏと논"
    },
    {
        "original": "지레저울",
        "transformed": "롱ㅏとㅣㅏㄹㅣと"
    },
    {
        "original": "국거리",
        "transformed": "ㅣㄹㅏㄴ논"
    },
    {
        "original": "겨울새",
        "transformed": "ㅐV롱ㅑㄴ"
    },
    {
        "original": "골패세",
        "transformed": "ㅣㅏVㅐㅍ룬"
    },
    {
        "original": "용기사",
        "transformed": "ㅓVㅣㄴ융"
    },
    {
        "original": "물레새",
        "transformed": "ㅐVㅣㅏㄹ롬"
    },
    {
        "original": "울대뼈",
        "transformed": "ㅑAAㅐ그롱"
    },
    {
        "original": "여욕",
        "transformed": "늉ㅑㅇ"
    },
    {
        "original": "사례물",
        "transformed": "롬ㅣㅑㄹㅓV"
    },
    {
        "original": "골계",
        "transformed": "ㅣㅑㄴ룬"
    },
    {
        "original": "용대기",
        "transformed": "ㅣㄴㅐ그융"
    },
    {
        "original": "놀놀이",
        "transformed": "ㅣㅇ룩룩"
    },
    {
        "original": "예풍",
        "transformed": "옾ㅣㅑㅇ"
    },
    {
        "original": "매목",
        "transformed": "눔ㅐㅁ"
    },
    {
        "original": "이기욕",
        "transformed": "늉ㅣㄴㅣㅇ"
    },
    {
        "original": "매곡",
        "transformed": "눈ㅐㅁ"
    },
    {
        "original": "애국",
        "transformed": "논ㅐㅇ"
    },
    {
        "original": "내군",
        "transformed": "곤ㅐㄱ"
    },
    {
        "original": "녹태",
        "transformed": "ㅐ彐눅"
    },
    {
        "original": "가공물",
        "transformed": "롬운ㅓㄴ"
    },
    {
        "original": "내용미",
        "transformed": "ㅣㅁ융ㅐㄱ"
    },
    {
        "original": "품재",
        "transformed": "ㅐと뫂"
    },
    {
        "original": "대사농",
        "transformed": "욱ㅓVㅐ그"
    },
    {
        "original": "제재목",
        "transformed": "눔ㅐとㅣㅏと"
    },
    {
        "original": "개풀",
        "transformed": "롶ㅐㄴ"
    },
    {
        "original": "문예지",
        "transformed": "ㅣとㅣㅑㅇ곰"
    },
    {
        "original": "올케",
        "transformed": "ㅣㅏヒ룽"
    },
    {
        "original": "어폐물",
        "transformed": "롬ㅣㅑㅍㅏㅇ"
    },
    {
        "original": "울이",
        "transformed": "ㅣㅇ롱"
    },
    {
        "original": "공놀이",
        "transformed": "ㅣㅇ룩운"
    },
    {
        "original": "눈싸움",
        "transformed": "몽ㅓW곡"
    },
    {
        "original": "곤가",
        "transformed": "ㅓㄴ군"
    },
    {
        "original": "세운",
        "transformed": "공ㅣㅏV"
    },
    {
        "original": "목내",
        "transformed": "ㅐㄱ눔"
    },
    {
        "original": "미공개",
        "transformed": "ㅐㄴ운ㅣㅁ"
    },
    {
        "original": "계목곡",
        "transformed": "눈눔ㅣㅑㄴ"
    },
    {
        "original": "하몽",
        "transformed": "움ㅓ우"
    },
    {
        "original": "공매매",
        "transformed": "ㅐㅁㅐㅁ운"
    },
    {
        "original": "시공품",
        "transformed": "뫂운ㅣV"
    },
    {
        "original": "사리골",
        "transformed": "룬ㅣㄹㅓV"
    },
    {
        "original": "농기세배",
        "transformed": "ㅐAㅣㅏVㅣㄴ욱"
    },
    {
        "original": "군사지물",
        "transformed": "롬ㅣとㅓV곤"
    },
    {
        "original": "게거품",
        "transformed": "뫂ㅏㄴㅣㅏㄴ"
    },
    {
        "original": "사자궁",
        "transformed": "온ㅓとㅓV"
    },
    {
        "original": "곤제",
        "transformed": "ㅣㅏと군"
    },
    {
        "original": "기공문",
        "transformed": "곰운ㅣㄴ"
    },
    {
        "original": "파서국",
        "transformed": "논ㅏVㅓㅍ"
    },
    {
        "original": "끼움",
        "transformed": "몽ㅣㄴㄴ"
    },
    {
        "original": "해군기",
        "transformed": "ㅣㄴ곤ㅐ우"
    },
    {
        "original": "용마",
        "transformed": "ㅓㅁ융"
    },
    {
        "original": "마디풀",
        "transformed": "롶ㅣ그ㅓㅁ"
    },
    {
        "original": "시운",
        "transformed": "공ㅣV"
    },
    {
        "original": "내폭",
        "transformed": "눞ㅐㄱ"
    },
    {
        "original": "떼싸움",
        "transformed": "몽ㅓWㅣㅏ그그"
    },
    {
        "original": "품제",
        "transformed": "ㅣㅏと뫂"
    },
    {
        "original": "나새목",
        "transformed": "눔ㅐVㅓㄱ"
    },
    {
        "original": "농어가",
        "transformed": "ㅓㄴㅏㅇ욱"
    },
    {
        "original": "공공사사",
        "transformed": "ㅓVㅓV운운"
    },
    {
        "original": "개골",
        "transformed": "룬ㅐㄴ"
    },
    {
        "original": "매용제",
        "transformed": "ㅣㅏと융ㅐㅁ"
    },
    {
        "original": "공야",
        "transformed": "ㅕㅇ운"
    },
    {
        "original": "서품",
        "transformed": "뫂ㅏV"
    },
    {
        "original": "파폭",
        "transformed": "눞ㅓㅍ"
    },
    {
        "original": "파파곡",
        "transformed": "눈ㅓㅍㅓㅍ"
    },
    {
        "original": "공기",
        "transformed": "ㅣㄴ운"
    },
    {
        "original": "여울목",
        "transformed": "눔롱ㅑㅇ"
    },
    {
        "original": "문해",
        "transformed": "ㅐ우곰"
    },
    {
        "original": "공대공",
        "transformed": "운ㅐ그운"
    },
    {
        "original": "매품",
        "transformed": "뫂ㅐㅁ"
    },
    {
        "original": "풍배",
        "transformed": "ㅐA옾"
    },
    {
        "original": "여공",
        "transformed": "운ㅑㅇ"
    },
    {
        "original": "더러움",
        "transformed": "몽ㅏㄹㅏ그"
    },
    {
        "original": "게문",
        "transformed": "곰ㅣㅏㄴ"
    },
    {
        "original": "저궁",
        "transformed": "온ㅏと"
    },
    {
        "original": "몽비",
        "transformed": "ㅣA움"
    },
    {
        "original": "배풍기",
        "transformed": "ㅣㄴ옾ㅐA"
    },
    {
        "original": "물거품",
        "transformed": "뫂ㅏㄴ롬"
    },
    {
        "original": "국폐",
        "transformed": "ㅣㅑㅍ논"
    },
    {
        "original": "미품",
        "transformed": "뫂ㅣㅁ"
    },
    {
        "original": "국기가",
        "transformed": "ㅓㄴㅣㄴ논"
    },
    {
        "original": "공계",
        "transformed": "ㅣㅑㄴ운"
    },
    {
        "original": "곤폐",
        "transformed": "ㅣㅑㅍ군"
    },
    {
        "original": "용골대",
        "transformed": "ㅐ그룬융"
    },
    {
        "original": "지계아문",
        "transformed": "곰ㅓㅇㅣㅑㄴㅣと"
    },
    {
        "original": "재공",
        "transformed": "운ㅐと"
    },
    {
        "original": "공배",
        "transformed": "ㅐA운"
    },
    {
        "original": "개물",
        "transformed": "롬ㅐㄴ"
    },
    {
        "original": "물아궁이",
        "transformed": "ㅣㅇ온ㅓㅇ롬"
    },
    {
        "original": "곡마",
        "transformed": "ㅓㅁ눈"
    },
    {
        "original": "개목사",
        "transformed": "ㅓV눔ㅐㄴ"
    },
    {
        "original": "몰아서기",
        "transformed": "ㅣㄴㅏVㅓㅇ룸"
    },
    {
        "original": "세문",
        "transformed": "곰ㅣㅏV"
    },
    {
        "original": "제궁",
        "transformed": "온ㅣㅏと"
    },
    {
        "original": "피공",
        "transformed": "운ㅣㅍ"
    },
    {
        "original": "대운하",
        "transformed": "ㅓ우공ㅐ그"
    },
    {
        "original": "대농가",
        "transformed": "ㅓㄴ욱ㅐ그"
    },
    {
        "original": "가제목",
        "transformed": "눔ㅣㅏとㅓㄴ"
    },
    {
        "original": "시군세",
        "transformed": "ㅣㅏV곤ㅣV"
    },
    {
        "original": "애기골풀",
        "transformed": "롶룬ㅣㄴㅐㅇ"
    },
    {
        "original": "올예",
        "transformed": "ㅣㅑㅇ룽"
    },
    {
        "original": "제군",
        "transformed": "곤ㅣㅏと"
    },
    {
        "original": "내품",
        "transformed": "뫂ㅐㄱ"
    },
    {
        "original": "매골",
        "transformed": "룬ㅐㅁ"
    },
    {
        "original": "세공물",
        "transformed": "롬운ㅣㅏV"
    },
    {
        "original": "타국",
        "transformed": "논ㅓ彐"
    },
    {
        "original": "녹자",
        "transformed": "ㅓと눅"
    },
    {
        "original": "바가지싸움",
        "transformed": "몽ㅓWㅣとㅓㄴㅓA"
    },
    {
        "original": "미나리나물",
        "transformed": "롬ㅓㄱㅣㄹㅓㄱㅣㅁ"
    },
    {
        "original": "태묵",
        "transformed": "놈ㅐ彐"
    },
    {
        "original": "눌어",
        "transformed": "ㅏㅇ록"
    },
    {
        "original": "굴기",
        "transformed": "ㅣㄴ론"
    },
    {
        "original": "폐풍",
        "transformed": "옾ㅣㅑㅍ"
    },
    {
        "original": "국태",
        "transformed": "ㅐ彐논"
    },
    {
        "original": "눈물바다",
        "transformed": "ㅓ그ㅓA롬곡"
    },
    {
        "original": "논매기",
        "transformed": "ㅣㄴㅐㅁ국"
    },
    {
        "original": "온제",
        "transformed": "ㅣㅏと궁"
    },
    {
        "original": "공리",
        "transformed": "ㅣㄹ운"
    },
    {
        "original": "가운데골",
        "transformed": "룬ㅣㅏ그공ㅓㄴ"
    },
    {
        "original": "지폭",
        "transformed": "눞ㅣと"
    },
    {
        "original": "여물",
        "transformed": "롬ㅑㅇ"
    },
    {
        "original": "내공목",
        "transformed": "눔운ㅐㄱ"
    },
    {
        "original": "애욕해",
        "transformed": "ㅐ우늉ㅐㅇ"
    },
    {
        "original": "시여물",
        "transformed": "롬ㅑㅇㅣV"
    },
    {
        "original": "묵계",
        "transformed": "ㅣㅑㄴ놈"
    },
    {
        "original": "거굴",
        "transformed": "론ㅏㄴ"
    },
    {
        "original": "제곡",
        "transformed": "눈ㅣㅏと"
    },
    {
        "original": "굴해",
        "transformed": "ㅐ우론"
    },
    {
        "original": "자라목",
        "transformed": "눔ㅓㄹㅓと"
    },
    {
        "original": "시공",
        "transformed": "운ㅣV"
    },
    {
        "original": "허허공공",
        "transformed": "운운ㅏ우ㅏ우"
    },
    {
        "original": "풀이씨",
        "transformed": "ㅣWㅣㅇ롶"
    },
    {
        "original": "궁서",
        "transformed": "ㅏV온"
    },
    {
        "original": "울타리",
        "transformed": "ㅣㄹㅓ彐롱"
    },
    {
        "original": "물애비",
        "transformed": "ㅣAㅐㅇ롬"
    },
    {
        "original": "너울",
        "transformed": "롱ㅏㄱ"
    },
    {
        "original": "폐문",
        "transformed": "곰ㅣㅑㅍ"
    },
    {
        "original": "개마디풀",
        "transformed": "롶ㅣ그ㅓㅁㅐㄴ"
    },
    {
        "original": "바디나물",
        "transformed": "롬ㅓㄱㅣ그ㅓA"
    },
    {
        "original": "태농",
        "transformed": "욱ㅐ彐"
    },
    {
        "original": "물나라",
        "transformed": "ㅓㄹㅓㄱ롬"
    },
    {
        "original": "옹자배기",
        "transformed": "ㅣㄴㅐAㅓと웅"
    },
    {
        "original": "파라풍",
        "transformed": "옾ㅓㄹㅓㅍ"
    },
    {
        "original": "목서",
        "transformed": "ㅏV눔"
    },
    {
        "original": "태운",
        "transformed": "공ㅐ彐"
    },
    {
        "original": "물세",
        "transformed": "ㅣㅏV롬"
    },
    {
        "original": "배녹사",
        "transformed": "ㅓV눅ㅐA"
    },
    {
        "original": "공시가",
        "transformed": "ㅓㄴㅣV운"
    },
    {
        "original": "다리목",
        "transformed": "눔ㅣㄹㅓ그"
    },
    {
        "original": "시계공",
        "transformed": "운ㅣㅑㄴㅣV"
    },
    {
        "original": "논리어",
        "transformed": "ㅏㅇㅣㄹ국"
    },
    {
        "original": "물매",
        "transformed": "ㅐㅁ롬"
    },
    {
        "original": "비녀골풀",
        "transformed": "롶룬ㅑㄱㅣA"
    },
    {
        "original": "해물",
        "transformed": "롬ㅐ우"
    },
    {
        "original": "미온욕",
        "transformed": "늉궁ㅣㅁ"
    },
    {
        "original": "농시",
        "transformed": "ㅣV욱"
    },
    {
        "original": "녹라",
        "transformed": "ㅓㄹ눅"
    },
    {
        "original": "농궁기",
        "transformed": "ㅣㄴ온욱"
    },
    {
        "original": "게시문",
        "transformed": "곰ㅣVㅣㅏㄴ"
    },
    {
        "original": "풀빼기",
        "transformed": "ㅣㄴㅐAA롶"
    },
    {
        "original": "웅자",
        "transformed": "ㅓと옹"
    },
    {
        "original": "마목",
        "transformed": "눔ㅓㅁ"
    },
    {
        "original": "새품",
        "transformed": "뫂ㅐV"
    },
    {
        "original": "공예",
        "transformed": "ㅣㅑㅇ운"
    },
    {
        "original": "울새",
        "transformed": "ㅐV롱"
    },
    {
        "original": "문공가례",
        "transformed": "ㅣㅑㄹㅓㄴ운곰"
    },
    {
        "original": "곡예",
        "transformed": "ㅣㅑㅇ눈"
    },
    {
        "original": "타목",
        "transformed": "눔ㅓ彐"
    },
    {
        "original": "해국",
        "transformed": "논ㅐ우"
    },
    {
        "original": "온풍기",
        "transformed": "ㅣㄴ옾궁"
    }
]